vaccine_stats/__init__.py
vaccine_stats/population.csv
vaccine_stats/vaccine_stats.py
vaccine_stats_ohio-2.0.1.dist-info/LICENSE
vaccine_stats_ohio-2.0.1.dist-info/METADATA
vaccine_stats_ohio-2.0.1.dist-info/WHEEL
vaccine_stats_ohio-2.0.1.dist-info/top_level.txt
vaccine_stats_ohio-2.0.1.dist-info/RECORD
