Metadata-Version: 2.1
Name: vaccine-stats-ohio
Version: 2.0.1
Summary: Access and summarize Ohio COVID vaccine statistics
Home-page: https://github.com/eddie-cosma/vaccine-stats-ohio
Author: Eddie Cosma
Author-email: vaxstat@eddiecosma.com
License: UNKNOWN
Platform: UNKNOWN
Classifier: Development Status :: 5 - Production/Stable
Classifier: License :: OSI Approved :: MIT License
Classifier: Operating System :: OS Independent
Classifier: Programming Language :: Python
Classifier: Programming Language :: Python :: 3
Requires-Python: >=3.9
License-File: LICENSE
